{"nodes": [{"id": "superpowers_sdd_task_4_brief_task4", "label": "Task 4 Brief: Atomic sortSeq", "file_type": "document", "source_file": ".superpowers/sdd/task-4-brief.md", "source_location": null, "source_url": null, "captured_at": null, "author": null, "contributor": null}], "edges": [{"source": "superpowers_sdd_task_4_brief_task4", "target": "docs_superpowers_plans_2026_07_01_pcn_register_4_hardening_atomic_sortseq", "relation": "implements", "confidence": "EXTRACTED", "confidence_score": 1.0, "source_file": ".superpowers/sdd/task-4-brief.md", "source_location": null, "weight": 1.0}], "hyperedges": []}